source/__init__.py
source/income_calculator.py
test/__init__.py
test/test_income_calculator.py
uk_tax_calculator_jld-0.0.1.dist-info/LICENSE
uk_tax_calculator_jld-0.0.1.dist-info/METADATA
uk_tax_calculator_jld-0.0.1.dist-info/WHEEL
uk_tax_calculator_jld-0.0.1.dist-info/top_level.txt
uk_tax_calculator_jld-0.0.1.dist-info/RECORD
